odoo8_addon_hr_recruitment_phone-8.0.0.1.0.99.dev5-py2.7-nspkg.pth
odoo8_addon_hr_recruitment_phone-8.0.0.1.0.99.dev5.dist-info/METADATA
odoo8_addon_hr_recruitment_phone-8.0.0.1.0.99.dev5.dist-info/RECORD
odoo8_addon_hr_recruitment_phone-8.0.0.1.0.99.dev5.dist-info/WHEEL
odoo8_addon_hr_recruitment_phone-8.0.0.1.0.99.dev5.dist-info/namespace_packages.txt
odoo8_addon_hr_recruitment_phone-8.0.0.1.0.99.dev5.dist-info/top_level.txt
odoo_addons/hr_recruitment_phone/__init__.py
odoo_addons/hr_recruitment_phone/__openerp__.py
odoo_addons/hr_recruitment_phone/hr_recruitment_phone.py
odoo_addons/hr_recruitment_phone/hr_recruitment_view.xml
odoo_addons/hr_recruitment_phone/i18n/es.po
odoo_addons/hr_recruitment_phone/i18n/fr.po
odoo_addons/hr_recruitment_phone/i18n/hr_recruitment_phone.pot
odoo_addons/hr_recruitment_phone/i18n/sl.po
odoo_addons/hr_recruitment_phone/i18n/tr.po
odoo_addons/hr_recruitment_phone/i18n/zh_CN.po
odoo_addons/hr_recruitment_phone/security/ir.model.access.csv
odoo_addons/hr_recruitment_phone/static/description/icon.png
